<odoo>
    <data>
        <record id="day_monday" model="days">
            <field name="name">Monday</field>
        </record>
        <record id="day_tuesday" model="days">
            <field name="name">Tuesday</field>
        </record>
        <record id="day_wednesday" model="days">
            <field name="name">Wednesday</field>
        </record>
        <record id="day_thursday" model="days">
            <field name="name">Thursday</field>
        </record>
        <record id="day_friday" model="days">
            <field name="name">Friday</field>
        </record>
        <record id="day_saturday" model="days">
            <field name="name">Saturday</field>
        </record>
        <record id="day_sunday" model="days">
            <field name="name">Sunday</field>
        </record>
    </data>
</odoo>
